ale_py-0.11.1.dist-info/RECORD
ale_py-0.11.1.dist-info/WHEEL
ale_py-0.11.1.dist-info/top_level.txt
ale_py-0.11.1.dist-info/METADATA
ale_py-0.11.1.dist-info/licenses/LICENSE.md
ale_py/registration.py
ale_py/ale_python_interface.hpp
ale_py/ale_vector_python_interface.hpp
ale_py/ale_vector_xla_interface.cpp
ale_py/CMakeLists.txt
ale_py/env.py
ale_py/_ale_py.cpython-39-darwin.so
ale_py/__init__.pyi
ale_py/vector_env.py
ale_py/libSDL2-2.0.0.dylib
ale_py/__init__.py
ale_py/py.typed
ale_py/ale_python_interface.cpp
ale_py/ale_vector_python_interface.cpp
ale_py/roms/asterix.bin
ale_py/roms/asteroids.bin
ale_py/roms/ms_pacman.bin
ale_py/roms/kaboom.bin
ale_py/roms/bank_heist.bin
ale_py/roms/backgammon.bin
ale_py/roms/klax.bin
ale_py/roms/crossbow.bin
ale_py/roms/combat.bin
ale_py/roms/kangaroo.bin
ale_py/roms/skiing.bin
ale_py/roms/fishing_derby.bin
ale_py/roms/krull.bin
ale_py/roms/flag_capture.bin
ale_py/roms/basic_math.bin
ale_py/roms/berzerk.bin
ale_py/roms/tutankham.bin
ale_py/roms/mario_bros.bin
ale_py/roms/zaxxon.bin
ale_py/roms/venture.bin
ale_py/roms/riverraid.bin
ale_py/roms/centipede.bin
ale_py/roms/word_zapper.bin
ale_py/roms/adventure.bin
ale_py/roms/warlords.bin
ale_py/roms/beam_rider.bin
ale_py/roms/crazy_climber.bin
ale_py/roms/time_pilot.bin
ale_py/roms/carnival.bin
ale_py/roms/tennis.bin
ale_py/roms/seaquest.bin
ale_py/roms/bowling.bin
ale_py/roms/space_invaders.bin
ale_py/roms/pitfall2.bin
ale_py/roms/freeway.bin
ale_py/roms/yars_revenge.bin
ale_py/roms/casino.bin
ale_py/roms/road_runner.bin
ale_py/roms/miniature_golf.bin
ale_py/roms/journey_escape.bin
ale_py/roms/wizard_of_wor.bin
ale_py/roms/donkey_kong.bin
ale_py/roms/gopher.bin
ale_py/roms/breakout.bin
ale_py/roms/star_gunner.bin
ale_py/roms/othello.bin
ale_py/roms/__init__.py
ale_py/roms/atlantis.bin
ale_py/roms/tic_tac_toe_3d.bin
ale_py/roms/double_dunk.bin
ale_py/roms/hero.bin
ale_py/roms/battle_zone.bin
ale_py/roms/tetris.bin
ale_py/roms/joust.bin
ale_py/roms/keystone_kapers.bin
ale_py/roms/solaris.bin
ale_py/roms/up_n_down.bin
ale_py/roms/frostbite.bin
ale_py/roms/video_checkers.bin
