Metadata-Version: 2.4
Name: ale-py
Version: 0.11.1
Summary: The Arcade Learning Environment (ALE) - a platform for AI research.
Author: Marc G. Bellemare, Yavar Naddaf, Joel Veness, Michael Bowling
Maintainer-email: Farama Foundation <contact@farama.org>, Jesse Farebrother <jfarebro@cs.mcgill.ca>
License-Expression: GPL-2.0-only
Project-URL: homepage, https://github.com/Farama-Foundation/Arcade-Learning-Environment
Project-URL: documentation, https://ale.farama.org
Project-URL: changelog, https://github.com/Farama-Foundation/Arcade-Learning-Environment/blob/master/CHANGELOG.md
Keywords: reinforcement-learning,arcade-learning-environment,atari
Classifier: Development Status :: 5 - Production/Stable
Classifier: Intended Audience :: Science/Research
Classifier: Programming Language :: Python :: 3
Classifier: Programming Language :: Python :: 3.9
Classifier: Programming Language :: Python :: 3.10
Classifier: Programming Language :: Python :: 3.11
Classifier: Programming Language :: Python :: 3.12
Classifier: Programming Language :: Python :: 3.13
Classifier: Topic :: Scientific/Engineering
Classifier: Topic :: Scientific/Engineering :: Artificial Intelligence
Requires-Python: >=3.9
License-File: LICENSE.md
Requires-Dist: numpy>1.20
Requires-Dist: importlib-metadata>=4.10.0; python_version < "3.10"
Requires-Dist: typing-extensions; python_version < "3.11"
Provides-Extra: vector
Requires-Dist: gymnasium>=1.1.0; extra == "vector"
Requires-Dist: opencv-python>=3.0; extra == "vector"
Provides-Extra: xla
Requires-Dist: gymnasium>=1.1.0; extra == "xla"
Requires-Dist: opencv-python>=3.0; extra == "xla"
Requires-Dist: jax>=0.4.31; (python_version > "3.9" and (sys_platform == "win32" or sys_platform == "linux")) and extra == "xla"
Provides-Extra: test
Requires-Dist: pytest>=7.0; extra == "test"
Requires-Dist: gymnasium>=1.1.0; extra == "test"
Requires-Dist: opencv-python>=3.0; extra == "test"
Requires-Dist: jax>=0.4.31; (python_version > "3.9" and (sys_platform == "win32" or sys_platform == "linux")) and extra == "test"
Requires-Dist: chex; (python_version > "3.9" and (sys_platform == "win32" or sys_platform == "linux")) and extra == "test"
Dynamic: license-file
